[
    {
        "key": "dbln",
        "value": "%7B%2261587390999870%22%3A%225ofx4lyi%22%2C%2261586143254191%22%3A%22ZcZ0aDU5%22%7D",
        "domain": "facebook.com",
        "path": "/login/device-based/",
        "hostOnly": false,
        "creation": "2026-02-13T15:51:50.708Z",
        "lastAccessed": "2026-02-13T15:51:50.708Z"
    },
    {
        "key": "datr",
        "value": "ORWMadKTB3Gi4o8eZZHveVkI",
        "domain": "facebook.com",
        "path": "/",
        "hostOnly": false,
        "creation": "2026-02-13T15:51:50.708Z",
        "lastAccessed": "2026-02-13T15:51:50.708Z"
    },
    {
        "key": "sb",
        "value": "ORWMaUgn0ilbg01KkqwSwNWA",
        "domain": "facebook.com",
        "path": "/",
        "hostOnly": false,
        "creation": "2026-02-13T15:51:50.708Z",
        "lastAccessed": "2026-02-13T15:51:50.708Z"
    },
    {
        "key": "vpd",
        "value": "v1%3B494x266x2.701960802078247",
        "domain": "facebook.com",
        "path": "/",
        "hostOnly": false,
        "creation": "2026-02-13T15:51:50.708Z",
        "lastAccessed": "2026-02-13T15:51:50.708Z"
    },
    {
        "key": "ps_l",
        "value": "1",
        "domain": "facebook.com",
        "path": "/",
        "hostOnly": false,
        "creation": "2026-02-13T15:51:50.708Z",
        "lastAccessed": "2026-02-13T15:51:50.708Z"
    },
    {
        "key": "ps_n",
        "value": "1",
        "domain": "facebook.com",
        "path": "/",
        "hostOnly": false,
        "creation": "2026-02-13T15:51:50.708Z",
        "lastAccessed": "2026-02-13T15:51:50.708Z"
    },
    {
        "key": "wl_cbv",
        "value": "v2%3Bclient_version%3A3081%3Btimestamp%3A1770991004",
        "domain": "facebook.com",
        "path": "/",
        "hostOnly": false,
        "creation": "2026-02-13T15:51:50.708Z",
        "lastAccessed": "2026-02-13T15:51:50.708Z"
    },
    {
        "key": "m_pixel_ratio",
        "value": "2.701960802078247",
        "domain": "facebook.com",
        "path": "/",
        "hostOnly": false,
        "creation": "2026-02-13T15:51:50.708Z",
        "lastAccessed": "2026-02-13T15:51:50.708Z"
    },
    {
        "key": "wd",
        "value": "360x800",
        "domain": "facebook.com",
        "path": "/",
        "hostOnly": false,
        "creation": "2026-02-13T15:51:50.708Z",
        "lastAccessed": "2026-02-13T15:51:50.708Z"
    },
    {
        "key": "c_user",
        "value": "61586143254191",
        "domain": "facebook.com",
        "path": "/",
        "hostOnly": false,
        "creation": "2026-02-13T15:51:50.708Z",
        "lastAccessed": "2026-02-13T15:51:50.708Z"
    },
    {
        "key": "xs",
        "value": "41%3AefB9Ivk1K_S_xQ%3A2%3A1770997702%3A-1%3A-1",
        "domain": "facebook.com",
        "path": "/",
        "hostOnly": false,
        "creation": "2026-02-13T15:51:50.708Z",
        "lastAccessed": "2026-02-13T15:51:50.708Z"
    },
    {
        "key": "fr",
        "value": "0Aj0T3kpdOLizQy6h.AWdRjPAak0OlP5N6Ir43UqBD3lJOS5d5PaRPJ4bI9usj5vQ_z6I.BpjBU5..AAA.0.0.Bpj0fd.AWcU12eSMA3eAxy4dN5ge1G5eP4",
        "domain": "facebook.com",
        "path": "/",
        "hostOnly": false,
        "creation": "2026-02-13T15:51:50.708Z",
        "lastAccessed": "2026-02-13T15:51:50.708Z"
    },
    {
        "key": "locale",
        "value": "en_GB",
        "domain": "facebook.com",
        "path": "/",
        "hostOnly": false,
        "creation": "2026-02-13T15:51:50.708Z",
        "lastAccessed": "2026-02-13T15:51:50.708Z"
    },
    {
        "key": "pas",
        "value": "61577722929012%3A9WForLJq42%2C61587390999870%3AC4zGV9NOHA%2C61586143254191%3AuVb88VPsuj",
        "domain": "facebook.com",
        "path": "/",
        "hostOnly": false,
        "creation": "2026-02-13T15:51:50.708Z",
        "lastAccessed": "2026-02-13T15:51:50.708Z"
    }
]